shakkala/Shakkala.py
shakkala/__init__.py
shakkala/demo.py
shakkala/helper.py
shakkala/dictionary/input_vocab_to_int.pickle
shakkala/dictionary/output_int_to_vocab.pickle
shakkala/model/middle_model.h5
shakkala/model/second_model6.h5
shakkala/model/simple_model.h5
shakkala-1.7.data/data/dictionary/input_vocab_to_int.pickle
shakkala-1.7.data/data/dictionary/output_int_to_vocab.pickle
shakkala-1.7.data/data/model/middle_model.h5
shakkala-1.7.data/data/model/second_model6.h5
shakkala-1.7.data/data/model/simple_model.h5
shakkala-1.7.dist-info/LICENSE.md
shakkala-1.7.dist-info/METADATA
shakkala-1.7.dist-info/WHEEL
shakkala-1.7.dist-info/top_level.txt
shakkala-1.7.dist-info/RECORD
