Metadata-Version: 2.1
Name: shakkala
Version: 1.7
Summary: Deep learning for Arabic text Vocalization - التشكيل الالي للنصوص العربية
Home-page: https://ahmadai.com/shakkala/
Author: Ahmad Albarqawi
License-File: LICENSE.md
Requires-Dist: tensorflow (==2.9.3)
Requires-Dist: h5py (==3.8.0)
Requires-Dist: nltk (==3.6.6)
Requires-Dist: numpy (==1.24.1)
Requires-Dist: click (==8.1.3)
